{
  "default": true,
  "elemente": [
    {
      "name": "CAPA",
      "typ": "Bf",
      "auto": true,
      "ordnung": 0,
      "sichtbar": true,
      "flags": ""
    },
    {
      "name": "CDUE",
      "typ": "Bf",
      "auto": true,
      "ordnung": 0,
      "sichtbar": true,
      "flags": ""
    },
    {
      "name": "DAD",
      "typ": "Bf",
      "auto": true,
      "ordnung": 0,
      "sichtbar": true,
      "flags": ""
    },
    {
      "name": "DAF",
      "typ": "Bf",
      "auto": true,
      "ordnung": 0,
      "sichtbar": true,
      "flags": ""
    },
    {
      "name": "DAGL",
      "typ": "Bf",
      "auto": true,
      "ordnung": 0,
      "sichtbar": true,
      "flags": ""
    },
    {
      "name": "DALT",
      "typ": "Bf",
      "auto": true,
      "ordnung": 0,
      "sichtbar": true,
      "flags": ""
    },
    {
      "name": "DAM",
      "typ": "Bf",
      "auto": true,
      "ordnung": 0,
      "sichtbar": true,
      "flags": ""
    },
    {
      "name": "DAV",
      "typ": "Bf",
      "auto": true,
      "ordnung": 0,
      "sichtbar": true,
      "flags": ""
    },
    {
      "name": "DAW",
      "typ": "Bf",
      "auto": true,
      "ordnung": 0,
      "sichtbar": true,
      "flags": ""
    },
    {
      "name": "FID",
      "typ": "Bf",
      "auto": true,
      "ordnung": 0,
      "sichtbar": true,
      "flags": ""
    },
    {
      "name": "FURN",
      "typ": "Bf",
      "auto": true,
      "ordnung": 0,
      "sichtbar": true,
      "flags": ""
    },
    {
      "name": "FUWI",
      "typ": "Bf",
      "auto": true,
      "ordnung": 0,
      "sichtbar": true,
      "flags": ""
    },
    {
      "name": "JAZ",
      "typ": "Bf",
      "auto": true,
      "ordnung": 0,
      "sichtbar": true,
      "flags": ""
    },
    {
      "name": "KLO",
      "typ": "Bf",
      "auto": true,
      "ordnung": 0,
      "sichtbar": true,
      "flags": ""
    },
    {
      "name": "KLOD",
      "typ": "Bf",
      "auto": true,
      "ordnung": 0,
      "sichtbar": true,
      "flags": ""
    },
    {
      "name": "KUEB",
      "typ": "Bf",
      "auto": true,
      "ordnung": 0,
      "sichtbar": true,
      "flags": ""
    },
    {
      "name": "SAAS",
      "typ": "Bf",
      "auto": true,
      "ordnung": 0,
      "sichtbar": true,
      "flags": ""
    },
    {
      "name": "SERN",
      "typ": "Bf",
      "auto": true,
      "ordnung": 0,
      "sichtbar": true,
      "flags": ""
    },
    {
      "name": "WIES",
      "typ": "Bf",
      "auto": true,
      "ordnung": 0,
      "sichtbar": true,
      "flags": ""
    },
    {
      "name": "CAPA",
      "typ": "Bft",
      "auto": false,
      "ordnung": 0,
      "sichtbar": true,
      "flags": "",
      "stamm": "CAPA"
    },
    {
      "name": "CAPA",
      "typ": "Bs",
      "auto": false,
      "ordnung": 0,
      "sichtbar": true,
      "flags": "",
      "stamm": "CAPA",
      "gleise": 1
    },
    {
      "name": "CAPA",
      "typ": "Gl",
      "auto": false,
      "ordnung": 0,
      "sichtbar": true,
      "flags": "",
      "stamm": "CAPA",
      "gleise": 1
    },
    {
      "name": "CDUE",
      "typ": "Bft",
      "auto": false,
      "ordnung": 0,
      "sichtbar": true,
      "flags": "",
      "stamm": "CDUE"
    },
    {
      "name": "CDUE 1",
      "typ": "Gl",
      "auto": false,
      "ordnung": 0,
      "sichtbar": true,
      "flags": "",
      "stamm": "CDUE 1",
      "gleise": 1
    },
    {
      "name": "CDUE 2",
      "typ": "Gl",
      "auto": false,
      "ordnung": 0,
      "sichtbar": true,
      "flags": "",
      "stamm": "CDUE 2",
      "gleise": 1
    },
    {
      "name": "DAD",
      "typ": "Bft",
      "auto": false,
      "ordnung": 0,
      "sichtbar": true,
      "flags": "",
      "stamm": "DAD"
    },
    {
      "name": "DAD 1",
      "typ": "Gl",
      "auto": false,
      "ordnung": 0,
      "sichtbar": true,
      "flags": "",
      "stamm": "DAD 1",
      "gleise": 1
    },
    {
      "name": "DAD 2",
      "typ": "Gl",
      "auto": false,
      "ordnung": 0,
      "sichtbar": true,
      "flags": "",
      "stamm": "DAD 2",
      "gleise": 1
    },
    {
      "name": "DAF",
      "typ": "Bft",
      "auto": false,
      "ordnung": 0,
      "sichtbar": true,
      "flags": "",
      "stamm": "DAF"
    },
    {
      "name": "DAF 1",
      "typ": "Gl",
      "auto": false,
      "ordnung": 0,
      "sichtbar": true,
      "flags": "",
      "stamm": "DAF 1",
      "gleise": 1
    },
    {
      "name": "DAF 2",
      "typ": "Gl",
      "auto": false,
      "ordnung": 0,
      "sichtbar": true,
      "flags": "",
      "stamm": "DAF 2",
      "gleise": 1
    },
    {
      "name": "DAGL",
      "typ": "Bft",
      "auto": false,
      "ordnung": 0,
      "sichtbar": true,
      "flags": "",
      "stamm": "DAGL"
    },
    {
      "name": "DAGL 2",
      "typ": "Gl",
      "auto": false,
      "ordnung": 0,
      "sichtbar": true,
      "flags": "",
      "stamm": "DAGL 2",
      "gleise": 1
    },
    {
      "name": "DAGL 1",
      "typ": "Gl",
      "auto": false,
      "ordnung": 0,
      "sichtbar": true,
      "flags": "",
      "stamm": "DAGL 1",
      "gleise": 1
    },
    {
      "name": "DALT",
      "typ": "Bft",
      "auto": false,
      "ordnung": 0,
      "sichtbar": true,
      "flags": "",
      "stamm": "DALT"
    },
    {
      "name": "DALT 1",
      "typ": "Gl",
      "auto": false,
      "ordnung": 0,
      "sichtbar": true,
      "flags": "",
      "stamm": "DALT 1",
      "gleise": 1
    },
    {
      "name": "DALT 2",
      "typ": "Gl",
      "auto": false,
      "ordnung": 0,
      "sichtbar": true,
      "flags": "",
      "stamm": "DALT 2",
      "gleise": 1
    },
    {
      "name": "DAM",
      "typ": "Bft",
      "auto": false,
      "ordnung": 0,
      "sichtbar": true,
      "flags": "",
      "stamm": "DAM"
    },
    {
      "name": "DAM",
      "typ": "Bs",
      "auto": false,
      "ordnung": 0,
      "sichtbar": true,
      "flags": "",
      "stamm": "DAM",
      "gleise": 1
    },
    {
      "name": "DAM",
      "typ": "Gl",
      "auto": false,
      "ordnung": 0,
      "sichtbar": true,
      "flags": "",
      "stamm": "DAM",
      "gleise": 1
    },
    {
      "name": "DAV 11",
      "typ": "Bft",
      "auto": true,
      "ordnung": 0,
      "sichtbar": true,
      "flags": "",
      "stamm": "DAV"
    },
    {
      "name": "DAV 50",
      "typ": "Bft",
      "auto": true,
      "ordnung": 0,
      "sichtbar": true,
      "flags": "",
      "stamm": "DAV"
    },
    {
      "name": "DAV 3",
      "typ": "Bft",
      "auto": false,
      "ordnung": 0,
      "sichtbar": true,
      "flags": "",
      "stamm": "DAV"
    },
    {
      "name": "DAV",
      "typ": "Bft",
      "auto": false,
      "ordnung": 0,
      "sichtbar": true,
      "flags": "",
      "stamm": "DAV"
    },
    {
      "name": "DAV 2A",
      "typ": "Gl",
      "auto": false,
      "ordnung": 0,
      "sichtbar": true,
      "flags": "",
      "stamm": "DAV 2",
      "gleise": 1
    },
    {
      "name": "DAV 2B",
      "typ": "Gl",
      "auto": false,
      "ordnung": 0,
      "sichtbar": true,
      "flags": "",
      "stamm": "DAV 2",
      "gleise": 1
    },
    {
      "name": "DAV 2",
      "typ": "Gl",
      "auto": false,
      "ordnung": 0,
      "sichtbar": true,
      "flags": "",
      "stamm": "DAV 2",
      "gleise": 1
    },
    {
      "name": "DAV 1",
      "typ": "Gl",
      "auto": false,
      "ordnung": 0,
      "sichtbar": true,
      "flags": "",
      "stamm": "DAV 1",
      "gleise": 1
    },
    {
      "name": "DAV 1A",
      "typ": "Gl",
      "auto": false,
      "ordnung": 0,
      "sichtbar": true,
      "flags": "",
      "stamm": "DAV 1",
      "gleise": 1
    },
    {
      "name": "DAV 1B",
      "typ": "Gl",
      "auto": false,
      "ordnung": 0,
      "sichtbar": true,
      "flags": "",
      "stamm": "DAV 1",
      "gleise": 1
    },
    {
      "name": "DAV 5",
      "typ": "Gl",
      "auto": false,
      "ordnung": 0,
      "sichtbar": true,
      "flags": "",
      "stamm": "DAV 5",
      "gleise": 1
    },
    {
      "name": "DAV 4",
      "typ": "Gl",
      "auto": false,
      "ordnung": 0,
      "sichtbar": true,
      "flags": "",
      "stamm": "DAV 4",
      "gleise": 1
    },
    {
      "name": "DAV 3",
      "typ": "Gl",
      "auto": false,
      "ordnung": 0,
      "sichtbar": true,
      "flags": "",
      "stamm": "DAV 3",
      "gleise": 1
    },
    {
      "name": "DAV 11",
      "typ": "Bs",
      "auto": true,
      "ordnung": 0,
      "sichtbar": true,
      "flags": "",
      "stamm": "DAV 11",
      "gleise": 1
    },
    {
      "name": "DAV 11",
      "typ": "Gl",
      "auto": true,
      "ordnung": 0,
      "sichtbar": true,
      "flags": "",
      "stamm": "DAV 11",
      "gleise": 1
    },
    {
      "name": "DAV 50",
      "typ": "Bs",
      "auto": true,
      "ordnung": 0,
      "sichtbar": true,
      "flags": "",
      "stamm": "DAV 50",
      "gleise": 1
    },
    {
      "name": "DAV 51",
      "typ": "Bs",
      "auto": true,
      "ordnung": 0,
      "sichtbar": true,
      "flags": "",
      "stamm": "DAV 50",
      "gleise": 1
    },
    {
      "name": "DAV 50",
      "typ": "Gl",
      "auto": true,
      "ordnung": 0,
      "sichtbar": true,
      "flags": "",
      "stamm": "DAV 50",
      "gleise": 1
    },
    {
      "name": "DAV 51",
      "typ": "Gl",
      "auto": true,
      "ordnung": 0,
      "sichtbar": true,
      "flags": "",
      "stamm": "DAV 51",
      "gleise": 1
    },
    {
      "name": "DAW",
      "typ": "Bft",
      "auto": false,
      "ordnung": 0,
      "sichtbar": true,
      "flags": "",
      "stamm": "DAW"
    },
    {
      "name": "DAW 1",
      "typ": "Gl",
      "auto": false,
      "ordnung": 0,
      "sichtbar": true,
      "flags": "",
      "stamm": "DAW 1",
      "gleise": 1
    },
    {
      "name": "DAW 2",
      "typ": "Gl",
      "auto": false,
      "ordnung": 0,
      "sichtbar": true,
      "flags": "",
      "stamm": "DAW 2",
      "gleise": 1
    },
    {
      "name": "FID",
      "typ": "Bft",
      "auto": false,
      "ordnung": 0,
      "sichtbar": true,
      "flags": "",
      "stamm": "FID"
    },
    {
      "name": "FID",
      "typ": "Bs",
      "auto": false,
      "ordnung": 0,
      "sichtbar": true,
      "flags": "",
      "stamm": "FID",
      "gleise": 1
    },
    {
      "name": "FID",
      "typ": "Gl",
      "auto": false,
      "ordnung": 0,
      "sichtbar": true,
      "flags": "",
      "stamm": "FID",
      "gleise": 1
    },
    {
      "name": "FURN",
      "typ": "Bft",
      "auto": false,
      "ordnung": 0,
      "sichtbar": true,
      "flags": "",
      "stamm": "FURN"
    },
    {
      "name": "FURN",
      "typ": "Bs",
      "auto": false,
      "ordnung": 0,
      "sichtbar": true,
      "flags": "",
      "stamm": "FURN",
      "gleise": 1
    },
    {
      "name": "FURN",
      "typ": "Gl",
      "auto": false,
      "ordnung": 0,
      "sichtbar": true,
      "flags": "",
      "stamm": "FURN",
      "gleise": 1
    },
    {
      "name": "FUWI",
      "typ": "Bft",
      "auto": false,
      "ordnung": 0,
      "sichtbar": true,
      "flags": "",
      "stamm": "FUWI"
    },
    {
      "name": "FUWI",
      "typ": "Bs",
      "auto": false,
      "ordnung": 0,
      "sichtbar": true,
      "flags": "",
      "stamm": "FUWI",
      "gleise": 1
    },
    {
      "name": "FUWI",
      "typ": "Gl",
      "auto": false,
      "ordnung": 0,
      "sichtbar": true,
      "flags": "",
      "stamm": "FUWI",
      "gleise": 1
    },
    {
      "name": "JAZ",
      "typ": "Bft",
      "auto": false,
      "ordnung": 0,
      "sichtbar": true,
      "flags": "",
      "stamm": "JAZ"
    },
    {
      "name": "JAZ",
      "typ": "Bs",
      "auto": false,
      "ordnung": 0,
      "sichtbar": true,
      "flags": "",
      "stamm": "JAZ",
      "gleise": 1
    },
    {
      "name": "JAZ",
      "typ": "Gl",
      "auto": false,
      "ordnung": 0,
      "sichtbar": true,
      "flags": "",
      "stamm": "JAZ",
      "gleise": 1
    },
    {
      "name": "KLO",
      "typ": "Bft",
      "auto": false,
      "ordnung": 0,
      "sichtbar": true,
      "flags": "",
      "stamm": "KLO"
    },
    {
      "name": "KLO 2B",
      "typ": "Gl",
      "auto": false,
      "ordnung": 0,
      "sichtbar": true,
      "flags": "",
      "stamm": "KLO 2",
      "gleise": 1
    },
    {
      "name": "KLO 2A",
      "typ": "Gl",
      "auto": false,
      "ordnung": 0,
      "sichtbar": true,
      "flags": "",
      "stamm": "KLO 2",
      "gleise": 1
    },
    {
      "name": "KLO 3B",
      "typ": "Gl",
      "auto": false,
      "ordnung": 0,
      "sichtbar": true,
      "flags": "",
      "stamm": "KLO 3",
      "gleise": 1
    },
    {
      "name": "KLO 3A",
      "typ": "Gl",
      "auto": false,
      "ordnung": 0,
      "sichtbar": true,
      "flags": "",
      "stamm": "KLO 3",
      "gleise": 1
    },
    {
      "name": "KLO 1",
      "typ": "Gl",
      "auto": false,
      "ordnung": 0,
      "sichtbar": true,
      "flags": "",
      "stamm": "KLO 1",
      "gleise": 1
    },
    {
      "name": "KLO 4",
      "typ": "Gl",
      "auto": false,
      "ordnung": 0,
      "sichtbar": true,
      "flags": "",
      "stamm": "KLO 4",
      "gleise": 1
    },
    {
      "name": "KLOD",
      "typ": "Bft",
      "auto": false,
      "ordnung": 0,
      "sichtbar": true,
      "flags": "",
      "stamm": "KLOD"
    },
    {
      "name": "KLOD 1",
      "typ": "Gl",
      "auto": false,
      "ordnung": 0,
      "sichtbar": true,
      "flags": "",
      "stamm": "KLOD 1",
      "gleise": 1
    },
    {
      "name": "KLOD 2",
      "typ": "Gl",
      "auto": false,
      "ordnung": 0,
      "sichtbar": true,
      "flags": "",
      "stamm": "KLOD 2",
      "gleise": 1
    },
    {
      "name": "KUEB 3",
      "typ": "Bft",
      "auto": false,
      "ordnung": 0,
      "sichtbar": true,
      "flags": "",
      "stamm": "KUEB"
    },
    {
      "name": "KUEB",
      "typ": "Bft",
      "auto": false,
      "ordnung": 0,
      "sichtbar": true,
      "flags": "",
      "stamm": "KUEB"
    },
    {
      "name": "KUEB 2",
      "typ": "Gl",
      "auto": false,
      "ordnung": 0,
      "sichtbar": true,
      "flags": "",
      "stamm": "KUEB 2",
      "gleise": 1
    },
    {
      "name": "KUEB 3",
      "typ": "Gl",
      "auto": false,
      "ordnung": 0,
      "sichtbar": true,
      "flags": "",
      "stamm": "KUEB 3",
      "gleise": 1
    },
    {
      "name": "KUEB 1",
      "typ": "Gl",
      "auto": false,
      "ordnung": 0,
      "sichtbar": true,
      "flags": "",
      "stamm": "KUEB 1",
      "gleise": 1
    },
    {
      "name": "SAAS",
      "typ": "Bft",
      "auto": false,
      "ordnung": 0,
      "sichtbar": true,
      "flags": "",
      "stamm": "SAAS"
    },
    {
      "name": "SAAS 2",
      "typ": "Gl",
      "auto": false,
      "ordnung": 0,
      "sichtbar": true,
      "flags": "",
      "stamm": "SAAS 2",
      "gleise": 1
    },
    {
      "name": "SAAS 1",
      "typ": "Gl",
      "auto": false,
      "ordnung": 0,
      "sichtbar": true,
      "flags": "",
      "stamm": "SAAS 1",
      "gleise": 1
    },
    {
      "name": "SERN",
      "typ": "Bft",
      "auto": false,
      "ordnung": 0,
      "sichtbar": true,
      "flags": "",
      "stamm": "SERN"
    },
    {
      "name": "SERN 2",
      "typ": "Gl",
      "auto": false,
      "ordnung": 0,
      "sichtbar": true,
      "flags": "",
      "stamm": "SERN 2",
      "gleise": 1
    },
    {
      "name": "SERN 1",
      "typ": "Gl",
      "auto": false,
      "ordnung": 0,
      "sichtbar": true,
      "flags": "",
      "stamm": "SERN 1",
      "gleise": 1
    },
    {
      "name": "WIES",
      "typ": "Bft",
      "auto": false,
      "ordnung": 0,
      "sichtbar": true,
      "flags": "",
      "stamm": "WIES"
    },
    {
      "name": "WIES 2",
      "typ": "Gl",
      "auto": false,
      "ordnung": 0,
      "sichtbar": true,
      "flags": "",
      "stamm": "WIES 2",
      "gleise": 1
    },
    {
      "name": "WIES 1",
      "typ": "Gl",
      "auto": false,
      "ordnung": 0,
      "sichtbar": true,
      "flags": "",
      "stamm": "WIES 1",
      "gleise": 1
    },
    {
      "name": "Schiers",
      "typ": "Anst",
      "auto": false,
      "ordnung": 0,
      "sichtbar": true,
      "flags": ""
    },
    {
      "name": "Büel",
      "typ": "Anst",
      "auto": false,
      "ordnung": 0,
      "sichtbar": true,
      "flags": ""
    },
    {
      "name": "Selfranga",
      "typ": "Anst",
      "auto": false,
      "ordnung": 0,
      "sichtbar": true,
      "flags": ""
    },
    {
      "name": "Filisur",
      "typ": "Anst",
      "auto": false,
      "ordnung": 0,
      "sichtbar": true,
      "flags": ""
    },
    {
      "name": "Abstellfeld",
      "typ": "Anst",
      "auto": false,
      "ordnung": 0,
      "sichtbar": true,
      "flags": ""
    },
    {
      "name": "Depot",
      "typ": "Anst",
      "auto": false,
      "ordnung": 0,
      "sichtbar": true,
      "flags": ""
    },
    {
      "name": "Schiers",
      "typ": "Agl",
      "auto": false,
      "ordnung": 0,
      "sichtbar": true,
      "flags": "",
      "stamm": "Schiers",
      "gleise": 1
    },
    {
      "name": "Büel",
      "typ": "Agl",
      "auto": false,
      "ordnung": 0,
      "sichtbar": true,
      "flags": "",
      "stamm": "Büel",
      "gleise": 1
    },
    {
      "name": "Selfranga",
      "typ": "Agl",
      "auto": false,
      "ordnung": 0,
      "sichtbar": true,
      "flags": "",
      "stamm": "Selfranga",
      "gleise": 1
    },
    {
      "name": "Filisur",
      "typ": "Agl",
      "auto": false,
      "ordnung": 0,
      "sichtbar": true,
      "flags": "",
      "stamm": "Filisur",
      "gleise": 1
    },
    {
      "name": "Abstellfeld",
      "typ": "Agl",
      "auto": false,
      "ordnung": 0,
      "sichtbar": true,
      "flags": "",
      "stamm": "Abstellfeld",
      "gleise": 1
    },
    {
      "name": "Depot",
      "typ": "Agl",
      "auto": false,
      "ordnung": 0,
      "sichtbar": true,
      "flags": "",
      "stamm": "Depot",
      "gleise": 1
    },
    {
      "name": "CDUE 1",
      "typ": "Bs",
      "auto": false,
      "ordnung": 0,
      "sichtbar": true,
      "flags": "",
      "stamm": "CDUE",
      "gleise": 1
    },
    {
      "name": "CDUE 2",
      "typ": "Bs",
      "auto": false,
      "ordnung": 0,
      "sichtbar": true,
      "flags": "",
      "stamm": "CDUE",
      "gleise": 1
    },
    {
      "name": "DAD 1",
      "typ": "Bs",
      "auto": false,
      "ordnung": 0,
      "sichtbar": true,
      "flags": "",
      "stamm": "DAD",
      "gleise": 1
    },
    {
      "name": "DAD 2",
      "typ": "Bs",
      "auto": false,
      "ordnung": 0,
      "sichtbar": true,
      "flags": "",
      "stamm": "DAD",
      "gleise": 1
    },
    {
      "name": "DAF 1",
      "typ": "Bs",
      "auto": false,
      "ordnung": 0,
      "sichtbar": true,
      "flags": "",
      "stamm": "DAF",
      "gleise": 1
    },
    {
      "name": "DAF 2",
      "typ": "Bs",
      "auto": false,
      "ordnung": 0,
      "sichtbar": true,
      "flags": "",
      "stamm": "DAF",
      "gleise": 1
    },
    {
      "name": "DAGL 2",
      "typ": "Bs",
      "auto": false,
      "ordnung": 0,
      "sichtbar": true,
      "flags": "",
      "stamm": "DAGL",
      "gleise": 1
    },
    {
      "name": "DAGL 1",
      "typ": "Bs",
      "auto": false,
      "ordnung": 0,
      "sichtbar": true,
      "flags": "",
      "stamm": "DAGL",
      "gleise": 1
    },
    {
      "name": "DALT 1",
      "typ": "Bs",
      "auto": false,
      "ordnung": 0,
      "sichtbar": true,
      "flags": "",
      "stamm": "DALT",
      "gleise": 1
    },
    {
      "name": "DALT 2",
      "typ": "Bs",
      "auto": false,
      "ordnung": 0,
      "sichtbar": true,
      "flags": "",
      "stamm": "DALT",
      "gleise": 1
    },
    {
      "name": "DAV 3",
      "typ": "Bs",
      "auto": false,
      "ordnung": 0,
      "sichtbar": true,
      "flags": "",
      "stamm": "DAV 3",
      "gleise": 1
    },
    {
      "name": "DAV 2",
      "typ": "Bs",
      "auto": false,
      "ordnung": 0,
      "sichtbar": true,
      "flags": "",
      "stamm": "DAV",
      "gleise": 1
    },
    {
      "name": "DAV 1",
      "typ": "Bs",
      "auto": false,
      "ordnung": 0,
      "sichtbar": true,
      "flags": "",
      "stamm": "DAV",
      "gleise": 1
    },
    {
      "name": "DAV 5",
      "typ": "Bs",
      "auto": false,
      "ordnung": 0,
      "sichtbar": true,
      "flags": "",
      "stamm": "DAV",
      "gleise": 1
    },
    {
      "name": "DAV 4",
      "typ": "Bs",
      "auto": false,
      "ordnung": 0,
      "sichtbar": true,
      "flags": "",
      "stamm": "DAV",
      "gleise": 1
    },
    {
      "name": "DAW 1",
      "typ": "Bs",
      "auto": false,
      "ordnung": 0,
      "sichtbar": true,
      "flags": "",
      "stamm": "DAW",
      "gleise": 1
    },
    {
      "name": "DAW 2",
      "typ": "Bs",
      "auto": false,
      "ordnung": 0,
      "sichtbar": true,
      "flags": "",
      "stamm": "DAW",
      "gleise": 1
    },
    {
      "name": "KLO 2",
      "typ": "Bs",
      "auto": false,
      "ordnung": 0,
      "sichtbar": true,
      "flags": "",
      "stamm": "KLO",
      "gleise": 1
    },
    {
      "name": "KLO 3",
      "typ": "Bs",
      "auto": false,
      "ordnung": 0,
      "sichtbar": true,
      "flags": "",
      "stamm": "KLO",
      "gleise": 1
    },
    {
      "name": "KLO 1",
      "typ": "Bs",
      "auto": false,
      "ordnung": 0,
      "sichtbar": true,
      "flags": "",
      "stamm": "KLO",
      "gleise": 1
    },
    {
      "name": "KLO 4",
      "typ": "Bs",
      "auto": false,
      "ordnung": 0,
      "sichtbar": true,
      "flags": "",
      "stamm": "KLO",
      "gleise": 1
    },
    {
      "name": "KLOD 1",
      "typ": "Bs",
      "auto": false,
      "ordnung": 0,
      "sichtbar": true,
      "flags": "",
      "stamm": "KLOD",
      "gleise": 1
    },
    {
      "name": "KLOD 2",
      "typ": "Bs",
      "auto": false,
      "ordnung": 0,
      "sichtbar": true,
      "flags": "",
      "stamm": "KLOD",
      "gleise": 1
    },
    {
      "name": "KUEB 3",
      "typ": "Bs",
      "auto": false,
      "ordnung": 0,
      "sichtbar": true,
      "flags": "",
      "stamm": "KUEB 3",
      "gleise": 1
    },
    {
      "name": "KUEB 2",
      "typ": "Bs",
      "auto": false,
      "ordnung": 0,
      "sichtbar": true,
      "flags": "",
      "stamm": "KUEB",
      "gleise": 1
    },
    {
      "name": "KUEB 1",
      "typ": "Bs",
      "auto": false,
      "ordnung": 0,
      "sichtbar": true,
      "flags": "",
      "stamm": "KUEB",
      "gleise": 1
    },
    {
      "name": "SAAS 2",
      "typ": "Bs",
      "auto": false,
      "ordnung": 0,
      "sichtbar": true,
      "flags": "",
      "stamm": "SAAS",
      "gleise": 1
    },
    {
      "name": "SAAS 1",
      "typ": "Bs",
      "auto": false,
      "ordnung": 0,
      "sichtbar": true,
      "flags": "",
      "stamm": "SAAS",
      "gleise": 1
    },
    {
      "name": "SERN 2",
      "typ": "Bs",
      "auto": false,
      "ordnung": 0,
      "sichtbar": true,
      "flags": "",
      "stamm": "SERN",
      "gleise": 1
    },
    {
      "name": "SERN 1",
      "typ": "Bs",
      "auto": false,
      "ordnung": 0,
      "sichtbar": true,
      "flags": "",
      "stamm": "SERN",
      "gleise": 1
    },
    {
      "name": "WIES 2",
      "typ": "Bs",
      "auto": false,
      "ordnung": 0,
      "sichtbar": true,
      "flags": "",
      "stamm": "WIES",
      "gleise": 1
    },
    {
      "name": "WIES 1",
      "typ": "Bs",
      "auto": false,
      "ordnung": 0,
      "sichtbar": true,
      "flags": "",
      "stamm": "WIES",
      "gleise": 1
    }
  ],
  "strecken": [
    {
      "name": "Schiers-Filisur",
      "haupt": false,
      "ordnung": 1,
      "auto": false,
      "stationen": [
        "Anst Schiers",
        "Bf FUWI",
        "Bf FURN",
        "Bf JAZ",
        "Bf FID",
        "Bf KUEB",
        "Bf CAPA",
        "Bf SAAS",
        "Bf SERN",
        "Bf KLOD",
        "Bf KLO",
        "Bf CDUE",
        "Bf DALT",
        "Bf DAW",
        "Bf DAD",
        "Bf DAV",
        "Bf DAF",
        "Bf DAGL",
        "Bf DAM",
        "Bf WIES",
        "Anst Filisur"
      ]
    },
    {
      "name": "Schiers-Selfranga",
      "haupt": false,
      "ordnung": 3,
      "auto": false,
      "stationen": [
        "Anst Schiers",
        "Bf FUWI",
        "Bf FURN",
        "Bf JAZ",
        "Bf FID",
        "Bf KUEB",
        "Bf CAPA",
        "Bf SAAS",
        "Bf SERN",
        "Bf KLOD",
        "Bf KLO",
        "Anst Selfranga"
      ]
    }
  ],
  "streckenmarkierung": [],
  "zugschema": "schweiz-rhb",
  "_aid": 710,
  "_build": 5851,
  "_name": "RhB / Klosters",
  "_region": "Ostschweiz",
  "_version": 3
}